main.py
ogre_36-0.1.0.dist-info/METADATA
ogre_36-0.1.0.dist-info/WHEEL
ogre_36-0.1.0.dist-info/top_level.txt
ogre_36-0.1.0.dist-info/RECORD
