Metadata-Version: 2.4
Name: ogre-36
Version: 0.1.0
Summary: Add your description here
Requires-Python: ~=3.6
Requires-Dist: geopandas>=0.9.0
Requires-Dist: networkx>=2.5.1
Requires-Dist: shapely>=1.8.5.post1
